snekspec/__init__.py
snekspec/core.py
snekspec/wiadro.py
snekspec-0.0.1.dist-info/LICENSE
snekspec-0.0.1.dist-info/METADATA
snekspec-0.0.1.dist-info/WHEEL
snekspec-0.0.1.dist-info/top_level.txt
snekspec-0.0.1.dist-info/RECORD
