Metadata-Version: 2.1
Name: snekspec
Version: 0.0.1
Summary: Validate data & generate test examples from scheme
Home-page: https://github.com/alexjuda/snekspec
Author: Alexander Juda
Author-email: alexanderjuda@gmail.com
License: UNKNOWN
Platform: UNKNOWN
Classifier: Programming Language :: Python :: 3
Classifier: License :: OSI Approved :: MIT License
Classifier: Operating System :: OS Independent
Classifier: Development Status :: 2 - Pre-Alpha
Classifier: Topic :: Software Development :: Testing
Classifier: Intended Audience :: Developers
Requires-Dist: hypothesis (>=4)
